CHANGELOG.txt
LICENCE.txt
MANIFEST.in
README.md
setup.py
snapmlengine/__init__.py
snapmlengine/main.py
snapmlengine.egg-info/PKG-INFO
snapmlengine.egg-info/SOURCES.txt
snapmlengine.egg-info/dependency_links.txt
snapmlengine.egg-info/requires.txt
snapmlengine.egg-info/top_level.txt
snapmlengine/ml/__init__.py
snapmlengine/ml/linear_regression.py